{
  "id": "cloudhand",
  "name": "CloudHand",
  "description": "Control your local Chrome browser. Bridges AI to your real browser via WebSocket.",
  "version": "2.7.0",
  "skills": ["./openclaw-skills"],
  "configSchema": {
    "type": "object",
    "additionalProperties": false,
    "properties": {
      "port": {
        "type": "number",
        "description": "WebSocket server port (default: 9876)"
      },
      "autoStart": {
        "type": "boolean",
        "description": "Auto-start the bridge server when Gateway starts (default: true)"
      },
      "localMode": {
        "type": "boolean",
        "description": "Enable local mode (binds to 127.0.0.1, skips pairing) (default: false)"
      }
    }
  },
  "uiHints": {
    "port": {
      "label": "Bridge Server Port",
      "help": "Port for the CloudHand WebSocket bridge server. Default: 9876."
    },
    "autoStart": {
      "label": "Auto Start",
      "help": "Automatically start the bridge server when OpenClaw Gateway starts."
    },
    "localMode": {
      "label": "Enable Local Mode",
      "help": "Enable local mode to bind bridge to 127.0.0.1 and skip pairing. Ideal for local AI agents."
    }
  }
}
